{
  "siteTitle": "2026 Youth Activities",
  "wardName": "Blackstone Ward",
  "quorumName": "Priests",
  "categories": [
    { "id": "social", "color": "#ec4899", "label": "Social" },
    { "id": "physical", "color": "#10b981", "label": "Physical" },
    { "id": "spiritual", "color": "#8b5cf6", "label": "Spiritual" },
    { "id": "intellectual", "color": "#f59e0b", "label": "Intellectual" },
    { "id": "combined", "color": "#3b82f6", "label": "Combined" }
  ],
  "scheduledEvents": [
    {"date":"2026-03-18","name":"Combined: Teachers","cat":"combined","details":"Combined activity led by the Teachers."},
    {"date":"2026-03-25","name":"Family History Basics","cat":"spiritual","details":"Bring your laptop or tablet best results. Caden to lead."},
    {"date":"2026-03-28","name":"King Street Cafe Breakfast","cat":"social","details":"Meet at King Street Cafe at 9:00 AM. 390 King Street Franklin, MA 02038"},
    {"date":"2026-04-01","name":"Digital Retro Games","cat":"social","details":"Tournament style retro gaming night."},
    {"date":"2026-04-08","name":"Make Pottery","cat":"intellectual","details":"Wear clothes that can get messy."},
    {"date":"2026-04-15","name":"Combined: Deacons","cat":"combined","details":"Combined activity led by the Deacons."},
    {"date":"2026-04-22","name":"Gospel Debate Night","cat":"spiritual","details":"Team debates on gospel topics like: Which BofM leader showed greatest faith?"},
    {"date":"2026-04-29","name":"Fishing","cat":"social","details":"Lake in Franklin...TBD"},
    {"date":"2026-05-06","name":"Musical Jam Session","cat":"social","details":"Bring your instruments! All skill levels welcome."},
    {"date":"2026-05-20","name":"Combined: YW","cat":"combined","details":"Combined activity led by the YW."},
    {"date":"2026-06-17","name":"Combined: Priests","cat":"combined","details":"Combined activity led by the Priests."},
    {"date":"2026-07-15","name":"Combined: Teachers","cat":"combined","details":"Combined activity led by the Teachers."},
    {"date":"2026-08-19","name":"Combined: Deacons","cat":"combined","details":"Combined activity led by the Deacons."},
    {"date":"2026-09-16","name":"Combined: YW","cat":"combined","details":"Combined activity led by the YW."},
    {"date":"2026-10-21","name":"Combined: Priests","cat":"combined","details":"Combined activity led by the Priests."},
    {"date":"2026-11-18","name":"Combined: Teachers","cat":"combined","details":"Combined activity led by the Teachers."},
    {"date":"2026-12-16","name":"Combined: Deacons","cat":"combined","details":"Combined activity led by the Deacons."}
  ],
  "unscheduledIdeas": [
    {"name":"Priest QM Cook-off + Cultural", "cat":"social", "details":""},
    {"name":"Pickleball tournament", "cat":"physical", "details":""},
    {"name":"Service: Pearl Street Cafe", "cat":"spiritual", "details":"Soup kitchen, set tables and serve"},
    {"name":"Service: Bishop's Store House", "cat":"spiritual", "details":"Ideally a combined activity"},
    {"name":"Rock climbing", "cat":"physical", "details":"Joseph to determine details"},
    {"name":"Fire & Picnic at the Beach", "cat":"physical", "details":"Point Judith RI on a Friday night"},
    {"name":"Martial Arts Class w/ John Cowden", "cat":"physical", "details":""},
    {"name":"Dig hole", "cat":"social", "details":""},
    {"name":"Basketball Tournament", "cat":"physical", "details":"Between 3 quorums"},
    {"name":"Assemble Ikea furniture", "cat":"intellectual", "details":"As a quorum"},
    {"name":"Car rocket soccer", "cat":"social", "details":""},
    {"name":"Scripture Story Renactment", "cat":"spiritual", "details":"Split into teams & assign a story"},
    {"name":"Ultimate frisbee", "cat":"physical", "details":""}
  ]
}